dicthash/__init__.py
dicthash/dicthash.py
dicthash-0.0.2.dist-info/METADATA
dicthash-0.0.2.dist-info/RECORD
dicthash-0.0.2.dist-info/WHEEL
dicthash-0.0.2.dist-info/top_level.txt
