Metadata-Version: 2.1
Name: dicthash
Version: 0.0.2
Summary: Generate portable md5 hashes from (arbitrarily nested) dictionaries.
Home-page: https://github.com/INM-6/python-dicthash
Author: Jakob Jordan, Maximilian Schmidt
Author-email: j.jordan@fz-juelich.de
License: MIT
Keywords: hashing hash
Platform: UNKNOWN
Classifier: Development Status :: 4 - Beta
Classifier: License :: OSI Approved :: GNU General Public License v2 (GPLv2)
Classifier: Natural Language :: English
Classifier: Operating System :: OS Independent
Classifier: Programming Language :: Python :: 2.7
Classifier: Programming Language :: Python :: 3.5
Classifier: Programming Language :: Python :: 3.6
Classifier: Topic :: Utilities
Requires-Python: >=2.7,!=3.0.*,!=3.1.*,!=3.2.*,!=3.3.*, !=3.4.*, <4
